odoo/addons/sm_reports/__init__.py
odoo/addons/sm_reports/__manifest__.py
odoo/addons/sm_reports/models/__init__.py
odoo/addons/sm_reports/models/models_sm_member.py
odoo/addons/sm_reports/security/ir.model.access.csv
odoo/addons/sm_reports/views/default_template.xml
odoo/addons/sm_reports/views/views_members.xml
odoo12_addon_sm_reports-12.0.0.0.3.dist-info/METADATA
odoo12_addon_sm_reports-12.0.0.0.3.dist-info/WHEEL
odoo12_addon_sm_reports-12.0.0.0.3.dist-info/top_level.txt
odoo12_addon_sm_reports-12.0.0.0.3.dist-info/RECORD
